dadosgerais.py
fcf.py
hidr.py
interc.py
mddh.py
planerg.py
pmo.py
resequiv.py
submercado.py
term.py
PyHydro/__init__.py
PyHydro/dadosgerais.py
PyHydro/fcf.py
PyHydro/hidr.py
PyHydro/interc.py
PyHydro/mddh.py
PyHydro/planerg.py
PyHydro/pmo.py
PyHydro/resequiv.py
PyHydro/submercado.py
PyHydro/term.py
hellotest_eduardo-0.0.9.dist-info/METADATA
hellotest_eduardo-0.0.9.dist-info/WHEEL
hellotest_eduardo-0.0.9.dist-info/top_level.txt
hellotest_eduardo-0.0.9.dist-info/RECORD
