Metadata-Version: 2.1
Name: hellotest-eduardo
Version: 0.0.9
Summary: PyHydro package
Home-page: https://bitbucket.org/eduardodeasousa/pyhydro-eduardo
Author: Eduardo
Author-email: eduardodeasousa@gmail.com
License: MIT
Keywords: pyhydro
Platform: UNKNOWN
Classifier: Development Status :: 5 - Production/Stable
Classifier: Intended Audience :: Developers
Classifier: Intended Audience :: Education
Classifier: License :: OSI Approved :: MIT License
Classifier: Operating System :: OS Independent
Classifier: Topic :: Scientific/Engineering :: Information Analysis
Classifier: Programming Language :: Python :: 3
Classifier: Programming Language :: Python :: 3.6
Classifier: Programming Language :: Python :: 3 :: Only
Requires-Python: >=3
Requires-Dist: cvxopt
Requires-Dist: matplotlib
Requires-Dist: numpy
Requires-Dist: pyswarm
Requires-Dist: scipy
Requires-Dist: typing
